pytailwindcss/__init__.py
pytailwindcss/__main__.py
pytailwindcss/exceptions.py
pytailwindcss/installation.py
pytailwindcss/utils.py
pytailwindcss-0.1.2.dist-info/entry_points.txt
pytailwindcss-0.1.2.dist-info/LICENSE
pytailwindcss-0.1.2.dist-info/WHEEL
pytailwindcss-0.1.2.dist-info/METADATA
pytailwindcss-0.1.2.dist-info/RECORD
