Metadata-Version: 2.1
Name: pytailwindcss
Version: 0.1.2
Summary: Standalone Tailwind CSS CLI, installable via pip. Use Tailwind CSS without Node.js.
Home-page: https://github.com/timonweb/pytailwindcss
License: MIT
Keywords: cli,tailwind,css
Author: Tim Kamanin
Author-email: tim@timonweb.com
Requires-Python: >=3.8,<4.0
Classifier: Development Status :: 4 - Beta
Classifier: Environment :: Web Environment
Classifier: Intended Audience :: Developers
Classifier: License :: OSI Approved :: MIT License
Classifier: Operating System :: OS Independent
Classifier: Programming Language :: Python :: 3
Classifier: Programming Language :: Python :: 3.10
Classifier: Programming Language :: Python :: 3.8
Classifier: Programming Language :: Python :: 3.9
Classifier: Topic :: Software Development :: Libraries
Classifier: Topic :: Utilities
